geospotter_api_py/DummyConnector.py
geospotter_api_py/GeoSpotterApi.py
geospotter_api_py/Node.py
geospotter_api_py/__init__.py
geospotter_api_py-0.0.3.dist-info/METADATA
geospotter_api_py-0.0.3.dist-info/WHEEL
geospotter_api_py-0.0.3.dist-info/licenses/LICENSE
geospotter_api_py-0.0.3.dist-info/RECORD
